subsetzer/__init__.py
subsetzer/__main__.py
subsetzer/chunking.py
subsetzer/cli.py
subsetzer/engine.py
subsetzer/io.py
subsetzer/logging_utils.py
subsetzer/py.typed
subsetzer/version.py
subsetzer/formats/__init__.py
subsetzer/formats/common.py
subsetzer/formats/srt.py
subsetzer/formats/tsv.py
subsetzer/formats/vtt.py
subsetzer-0.1.4.dist-info/METADATA
subsetzer-0.1.4.dist-info/WHEEL
subsetzer-0.1.4.dist-info/entry_points.txt
subsetzer-0.1.4.dist-info/licenses/LICENSE
subsetzer-0.1.4.dist-info/RECORD
