Metadata-Version: 2.4
Name: subsetzer
Version: 0.1.4
Summary: Translate SRT/VTT/TSV via a local LLM (Ollama-compatible). CLI-first; stdlib-only core.
Project-URL: Homepage, https://github.com/githabideri/subsetzer
Project-URL: Issues, https://github.com/githabideri/subsetzer/issues
Author-email: Martin Fellner <martin@martinfellner.at>
License-Expression: GPL-3.0-or-later
License-File: LICENSE
Keywords: ollama,srt,subtitles,translation,vtt
Classifier: Environment :: Console
Classifier: License :: OSI Approved :: GNU General Public License v3 or later (GPLv3+)
Classifier: Operating System :: OS Independent
Classifier: Programming Language :: Python :: 3
Classifier: Topic :: Utilities
Requires-Python: >=3.9
